{
	"credit": "Made with Blockbench",
	"parent": "minecraft:block/block",
	"texture_size": [32, 32],
	"textures": {
		"0": "another_furniture:block/picket_fence/oak"
	},
	"elements": [
		{
			"from": [0, 1, 7],
			"to": [6, 4, 9],
			"faces": {
				"north": {"uv": [9, 7, 12, 8.5], "texture": "#0"},
				"east": {"uv": [8, 7, 9, 8.5], "texture": "#0"},
				"south": {"uv": [13, 7, 16, 8.5], "texture": "#0"},
				"west": {"uv": [12, 7, 13, 8.5], "texture": "#0"},
				"up": {"uv": [12, 7, 9, 6], "texture": "#0"},
				"down": {"uv": [15, 6, 12, 7], "texture": "#0", "cullface": "down"}
			}
		},
		{
			"from": [0, 4, 8],
			"to": [6, 16, 8],
			"rotation": {"angle": 0, "axis": "y", "origin": [16, 0, 0]},
			"faces": {
				"north": {"uv": [8, 0, 11, 6], "texture": "#0"},
				"east": {"uv": [8, 0, 8, 6], "texture": "#0"},
				"south": {"uv": [11, 0, 14, 6], "texture": "#0"},
				"west": {"uv": [11, 0, 11, 6], "texture": "#0"},
				"up": {"uv": [11, 0, 8, 0], "texture": "#0"},
				"down": {"uv": [14, 0, 11, 0], "texture": "#0", "cullface": "down"}
			}
		},
		{
			"from": [6, 0, 6],
			"to": [10, 16, 10],
			"faces": {
				"north": {"uv": [2, 2, 4, 10], "texture": "#0"},
				"east": {"uv": [0, 2, 2, 10], "texture": "#0"},
				"south": {"uv": [6, 2, 8, 10], "texture": "#0"},
				"west": {"uv": [4, 2, 6, 10], "texture": "#0"},
				"up": {"uv": [4, 2, 2, 0], "texture": "#0"},
				"down": {"uv": [6, 0, 4, 2], "texture": "#0", "cullface": "down"}
			}
		},
		{
			"from": [0, 9, 7],
			"to": [6, 12, 9],
			"faces": {
				"north": {"uv": [9, 7, 12, 8.5], "texture": "#0"},
				"east": {"uv": [8, 7, 9, 8.5], "texture": "#0"},
				"south": {"uv": [13, 7, 16, 8.5], "texture": "#0"},
				"west": {"uv": [12, 7, 13, 8.5], "texture": "#0"},
				"up": {"uv": [12, 7, 9, 6], "texture": "#0"},
				"down": {"uv": [15, 6, 12, 7], "texture": "#0", "cullface": "down"}
			}
		}
	]
}